[
  {
    "id": 1,
      "attributes": {
        "slug": "olha-so-minha-pagina",
        "createdAt": "2023-01-06T23:28:51.333Z",
        "updatedAt": "2023-05-11T13:47:37.989Z",
        "publishedAt": "2023-05-11T13:47:37.539Z",
        "footer_text": "Fale com ❤ para Marcos Paulo",
        "sections": [
          {
            "id": 1,
            "component": "section.section-two-columns",
            "title": "teste 1",
            "description": "descrição",
            "image": {
              "data": {
                "id": 10,
                "attributes": {
                  "name": "javascript.svg",
                  "alternativeText": null,
                  "caption": null,
                  "width": 1030,
                  "height": 730,
                  "formats": null,
                  "hash": "javascript_e0d7190dcf",
                  "ext": ".svg",
                  "mime": "image/svg+xml",
                  "size": 30.31,
                  "url": "https://res.cloudinary.com/dfrbl33eq/image/upload/v1683809448/javascript_e0d7190dcf.svg",
                  "previewUrl": null,
                  "provider": "cloudinary",
                  "provider_metadata": {
                    "public_id": "javascript_e0d7190dcf",
                    "resource_type": "image"
                  },
                  "createdAt": "2023-05-11T12:50:49.915Z",
                  "updatedAt": "2023-05-11T12:50:49.915Z"
                }
              }
            },
            "metadata": {
              "id": 1,
              "name": "home",
              "section_id": "home",
              "background": true
            }
          },
          {
            "id": 1,
            "__component": "section.section-content",
            "title": "Section Content",
            "content": "Esta é uma breve descrição para esta **seção**",
            "metadata": {
              "id": 3,
              "name": "intro",
              "section_id": "intro",
              "background": false
            }
          },
          {
            "id": 1,
            "__component": "section.section-grid",
            "title": "My grid",
            "description": "descrição grid",
            "metadata": {
              "id": 2,
              "name": "grid-one",
              "section_id": "grid-one",
              "background": true
            },
            "text_grid": [
              {
                "id": 1,
                "title": "teste 1",
                "description": "descrição 1"
              },
              {
                "id": 2,
                "title": "teste 2",
                "description": "descrição 2"
              },
              {
                "id": 3,
                "title": "teste 3",
                "description": "descrição 3"
              }
            ],
            "image_grid": [

            ]
          },
          {
            "id": 2,
            "__component": "section.section-grid",
            "title": "GALLERY",
            "description": "Uma breve descrição.",
            "metadata": {
              "id": 4,
              "name": "gallery",
              "section_id": "gallery-one",
              "background": false
            },
            "text_grid": [

            ],
            "image_grid": [
              {
                "id": 1,
                "image": {
                  "data": [
                    {
                      "id": 9,
                      "attributes": {
                        "name": "photo-1596918638939-cf4d365b6e03.jpg",
                        "alternativeText": "Bufalo",
                        "caption": null,
                        "width": 360,
                        "height": 360,
                        "formats": {
                          "thumbnail": {
                            "ext": ".jpg",
                            "url": "https://res.cloudinary.com/dfrbl33eq/image/upload/v1683563522/thumbnail_photo_1596918638939_cf4d365b6e03_09f9387328.jpg",
                            "hash": "thumbnail_photo_1596918638939_cf4d365b6e03_09f9387328",
                            "mime": "image/jpeg",
                            "name": "thumbnail_photo-1596918638939-cf4d365b6e03.jpg",
                            "path": null,
                            "size": 6.95,
                            "width": 156,
                            "height": 156,
                            "provider_metadata": {
                              "public_id": "thumbnail_photo_1596918638939_cf4d365b6e03_09f9387328",
                              "resource_type": "image"
                            }
                          }
                        },
                        "hash": "photo_1596918638939_cf4d365b6e03_09f9387328",
                        "ext": ".jpg",
                        "mime": "image/jpeg",
                        "size": 31.34,
                        "url": "https://res.cloudinary.com/dfrbl33eq/image/upload/v1683563522/photo_1596918638939_cf4d365b6e03_09f9387328.jpg",
                        "previewUrl": null,
                        "provider": "cloudinary",
                        "provider_metadata": {
                          "public_id": "photo_1596918638939_cf4d365b6e03_09f9387328",
                          "resource_type": "image"
                        },
                        "createdAt": "2023-05-08T16:32:03.295Z",
                        "updatedAt": "2023-05-08T16:53:22.614Z"
                      }
                    },
                    {
                      "id": 8,
                      "attributes": {
                        "name": "photo-1610725424565-e12038af85a8.jpg",
                        "alternativeText": "carro",
                        "caption": null,
                        "width": 360,
                        "height": 360,
                        "formats": {
                          "thumbnail": {
                            "ext": ".jpg",
                            "url": "https://res.cloudinary.com/dfrbl33eq/image/upload/v1683563522/thumbnail_photo_1610725424565_e12038af85a8_544ce1b22f.jpg",
                            "hash": "thumbnail_photo_1610725424565_e12038af85a8_544ce1b22f",
                            "mime": "image/jpeg",
                            "name": "thumbnail_photo-1610725424565-e12038af85a8.jpg",
                            "path": null,
                            "size": 5.41,
                            "width": 156,
                            "height": 156,
                            "provider_metadata": {
                              "public_id": "thumbnail_photo_1610725424565_e12038af85a8_544ce1b22f",
                              "resource_type": "image"
                            }
                          }
                        },
                        "hash": "photo_1610725424565_e12038af85a8_544ce1b22f",
                        "ext": ".jpg",
                        "mime": "image/jpeg",
                        "size": 21.35,
                        "url": "https://res.cloudinary.com/dfrbl33eq/image/upload/v1683563522/photo_1610725424565_e12038af85a8_544ce1b22f.jpg",
                        "previewUrl": null,
                        "provider": "cloudinary",
                        "provider_metadata": {
                          "public_id": "photo_1610725424565_e12038af85a8_544ce1b22f",
                          "resource_type": "image"
                        },
                        "createdAt": "2023-05-08T16:32:02.706Z",
                        "updatedAt": "2023-05-08T16:50:25.120Z"
                      }
                    },
                    {
                      "id": 7,
                      "attributes": {
                        "name": "photo-1548430691-a027e3a8f23d.jpg",
                        "alternativeText": "moto",
                        "caption": null,
                        "width": 360,
                        "height": 360,
                        "formats": {
                          "thumbnail": {
                            "ext": ".jpg",
                            "url": "https://res.cloudinary.com/dfrbl33eq/image/upload/v1683563522/thumbnail_photo_1548430691_a027e3a8f23d_e6ec9b65c5.jpg",
                            "hash": "thumbnail_photo_1548430691_a027e3a8f23d_e6ec9b65c5",
                            "mime": "image/jpeg",
                            "name": "thumbnail_photo-1548430691-a027e3a8f23d.jpg",
                            "path": null,
                            "size": 3.52,
                            "width": 156,
                            "height": 156,
                            "provider_metadata": {
                              "public_id": "thumbnail_photo_1548430691_a027e3a8f23d_e6ec9b65c5",
                              "resource_type": "image"
                            }
                          }
                        },
                        "hash": "photo_1548430691_a027e3a8f23d_e6ec9b65c5",
                        "ext": ".jpg",
                        "mime": "image/jpeg",
                        "size": 10.88,
                        "url": "https://res.cloudinary.com/dfrbl33eq/image/upload/v1683563522/photo_1548430691_a027e3a8f23d_e6ec9b65c5.jpg",
                        "previewUrl": null,
                        "provider": "cloudinary",
                        "provider_metadata": {
                          "public_id": "photo_1548430691_a027e3a8f23d_e6ec9b65c5",
                          "resource_type": "image"
                        },
                        "createdAt": "2023-05-08T16:32:02.546Z",
                        "updatedAt": "2023-05-08T16:50:34.809Z"
                      }
                    },
                    {
                      "id": 6,
                      "attributes": {
                        "name": "photo-1645733783782-0c91d525f622.jpg",
                        "alternativeText": "moto-estilosa",
                        "caption": null,
                        "width": 360,
                        "height": 360,
                        "formats": {
                          "thumbnail": {
                            "ext": ".jpg",
                            "url": "https://res.cloudinary.com/dfrbl33eq/image/upload/v1683563521/thumbnail_photo_1645733783782_0c91d525f622_3c65b26d98.jpg",
                            "hash": "thumbnail_photo_1645733783782_0c91d525f622_3c65b26d98",
                            "mime": "image/jpeg",
                            "name": "thumbnail_photo-1645733783782-0c91d525f622.jpg",
                            "path": null,
                            "size": 3.73,
                            "width": 156,
                            "height": 156,
                            "provider_metadata": {
                              "public_id": "thumbnail_photo_1645733783782_0c91d525f622_3c65b26d98",
                              "resource_type": "image"
                            }
                          }
                        },
                        "hash": "photo_1645733783782_0c91d525f622_3c65b26d98",
                        "ext": ".jpg",
                        "mime": "image/jpeg",
                        "size": 11.71,
                        "url": "https://res.cloudinary.com/dfrbl33eq/image/upload/v1683563521/photo_1645733783782_0c91d525f622_3c65b26d98.jpg",
                        "previewUrl": null,
                        "provider": "cloudinary",
                        "provider_metadata": {
                          "public_id": "photo_1645733783782_0c91d525f622_3c65b26d98",
                          "resource_type": "image"
                        },
                        "createdAt": "2023-05-08T16:32:02.067Z",
                        "updatedAt": "2023-05-08T16:50:54.030Z"
                      }
                    }
                  ]
                }
              }
            ]
          }
        ],
        "menu": {
          "id": 1,
          "logo_link": "#home",
          "logo_text": "Logo",
          "logo": {
            "data": {
              "id": 5,
              "attributes": {
                "name": "Cool-Example-Company-Logo-33-For-Logo-Inspiration-with-Example-Company-Logo-e1504694443294.png",
                "alternativeText": "teste",
                "caption": null,
                "width": 750,
                "height": 303,
                "formats": {
                  "small": {
                    "ext": ".png",
                    "url": "https://res.cloudinary.com/dfrbl33eq/image/upload/v1683555923/small_Cool_Example_Company_Logo_33_For_Logo_Inspiration_with_Example_Company_Logo_e1504694443294_3eb16f8657.png",
                    "hash": "small_Cool_Example_Company_Logo_33_For_Logo_Inspiration_with_Example_Company_Logo_e1504694443294_3eb16f8657",
                    "mime": "image/png",
                    "name": "small_Cool-Example-Company-Logo-33-For-Logo-Inspiration-with-Example-Company-Logo-e1504694443294.png",
                    "path": null,
                    "size": 42.67,
                    "width": 500,
                    "height": 202,
                    "provider_metadata": {
                      "public_id": "small_Cool_Example_Company_Logo_33_For_Logo_Inspiration_with_Example_Company_Logo_e1504694443294_3eb16f8657",
                      "resource_type": "image"
                    }
                  },
                  "thumbnail": {
                    "ext": ".png",
                    "url": "https://res.cloudinary.com/dfrbl33eq/image/upload/v1683555922/thumbnail_Cool_Example_Company_Logo_33_For_Logo_Inspiration_with_Example_Company_Logo_e1504694443294_3eb16f8657.png",
                    "hash": "thumbnail_Cool_Example_Company_Logo_33_For_Logo_Inspiration_with_Example_Company_Logo_e1504694443294_3eb16f8657",
                    "mime": "image/png",
                    "name": "thumbnail_Cool-Example-Company-Logo-33-For-Logo-Inspiration-with-Example-Company-Logo-e1504694443294.png",
                    "path": null,
                    "size": 12.76,
                    "width": 245,
                    "height": 99,
                    "provider_metadata": {
                      "public_id": "thumbnail_Cool_Example_Company_Logo_33_For_Logo_Inspiration_with_Example_Company_Logo_e1504694443294_3eb16f8657",
                      "resource_type": "image"
                    }
                  }
                },
                "hash": "Cool_Example_Company_Logo_33_For_Logo_Inspiration_with_Example_Company_Logo_e1504694443294_3eb16f8657",
                "ext": ".png",
                "mime": "image/png",
                "size": 18.56,
                "url": "https://res.cloudinary.com/dfrbl33eq/image/upload/v1683555922/Cool_Example_Company_Logo_33_For_Logo_Inspiration_with_Example_Company_Logo_e1504694443294_3eb16f8657.png",
                "previewUrl": null,
                "provider": "cloudinary",
                "provider_metadata": {
                  "public_id": "Cool_Example_Company_Logo_33_For_Logo_Inspiration_with_Example_Company_Logo_e1504694443294_3eb16f8657",
                  "resource_type": "image"
                },
                "createdAt": "2023-05-08T14:25:24.156Z",
                "updatedAt": "2023-05-11T17:04:40.891Z"
              }
            }
          },
          "menu_links": [
            {
              "id": 1,
              "link_text": "intro",
              "url": "#intro",
              "open_in_new_tab": false
            },
            {
              "id": 2,
              "link_text": "grid-one",
              "url": "#grid-one",
              "open_in_new_tab": false
            }
          ]
        }
      }

  }
]
